Metadata-Version: 2.1
Name: x2vmlgml
Version: 99.7
Summary: x
Author: x
Author-email: xxx@outlook.com
Requires-Dist: requests
